{"crate":{"created_at":"2014-11-23T17:40:16Z","description":"A full STOMP 1.2 client implementation. Allows programs to interact with message queueing services like ActiveMQ and RabbitMQ.","documentation":null,"downloads":744,"homepage":null,"id":"stomp","keywords":["stomp","mq","activemq","rabbitmq","queue"],"license":"MIT","links":{"owners":"/api/v1/crates/stomp/owners","reverse_dependencies":"/api/v1/crates/stomp/reverse_dependencies","version_downloads":"/api/v1/crates/stomp/downloads","versions":null},"max_version":"0.11.0","name":"stomp","repository":"https://github.com/zslayton/stomp-rs","updated_at":"2015-12-16T00:01:56Z","versions":[14974,13840,11018,10818,9609,8172,7504,7144,5920,4760,4747,4554,4263,4139,3952,3468,2813,2284,2283,1455,561]},"keywords":[{"crates_cnt":2,"created_at":"2014-11-23T17:40:16Z","id":"rabbitmq","keyword":"rabbitmq"},{"crates_cnt":1,"created_at":"2014-11-23T17:40:16Z","id":"activemq","keyword":"activemq"},{"crates_cnt":13,"created_at":"2014-11-23T17:40:16Z","id":"queue","keyword":"queue"},{"crates_cnt":1,"created_at":"2014-11-23T17:40:16Z","id":"mq","keyword":"mq"},{"crates_cnt":1,"created_at":"2014-11-23T17:40:16Z","id":"stomp","keyword":"stomp"}],"versions":[{"crate":"stomp","created_at":"2015-08-24T19:50:04Z","dl_path":"/api/v1/crates/stomp/0.11.0/download","downloads":365,"features":{},"id":14974,"links":{"authors":"/api/v1/crates/stomp/0.11.0/authors","dependencies":"/api/v1/crates/stomp/0.11.0/dependencies","version_downloads":"/api/v1/crates/stomp/0.11.0/downloads"},"num":"0.11.0","updated_at":"2015-12-16T00:01:56Z","yanked":false},{"crate":"stomp","created_at":"2015-07-29T20:38:47Z","dl_path":"/api/v1/crates/stomp/0.10.2/download","downloads":56,"features":{},"id":13840,"links":{"authors":"/api/v1/crates/stomp/0.10.2/authors","dependencies":"/api/v1/crates/stomp/0.10.2/dependencies","version_downloads":"/api/v1/crates/stomp/0.10.2/downloads"},"num":"0.10.2","updated_at":"2015-12-11T23:56:18Z","yanked":false},{"crate":"stomp","created_at":"2015-05-29T18:52:01Z","dl_path":"/api/v1/crates/stomp/0.10.1/download","downloads":69,"features":{},"id":11018,"links":{"authors":"/api/v1/crates/stomp/0.10.1/authors","dependencies":"/api/v1/crates/stomp/0.10.1/dependencies","version_downloads":"/api/v1/crates/stomp/0.10.1/downloads"},"num":"0.10.1","updated_at":"2015-12-11T23:56:18Z","yanked":false},{"crate":"stomp","created_at":"2015-05-27T03:44:03Z","dl_path":"/api/v1/crates/stomp/0.10.0/download","downloads":11,"features":{},"id":10818,"links":{"authors":"/api/v1/crates/stomp/0.10.0/authors","dependencies":"/api/v1/crates/stomp/0.10.0/dependencies","version_downloads":"/api/v1/crates/stomp/0.10.0/downloads"},"num":"0.10.0","updated_at":"2015-12-11T23:56:18Z","yanked":false},{"crate":"stomp","created_at":"2015-04-29T20:45:38Z","dl_path":"/api/v1/crates/stomp/0.9.0/download","downloads":29,"features":{},"id":9609,"links":{"authors":"/api/v1/crates/stomp/0.9.0/authors","dependencies":"/api/v1/crates/stomp/0.9.0/dependencies","version_downloads":"/api/v1/crates/stomp/0.9.0/downloads"},"num":"0.9.0","updated_at":"2015-12-11T23:56:18Z","yanked":false},{"crate":"stomp","created_at":"2015-04-05T15:25:16Z","dl_path":"/api/v1/crates/stomp/0.8.4/download","downloads":27,"features":{},"id":8172,"links":{"authors":"/api/v1/crates/stomp/0.8.4/authors","dependencies":"/api/v1/crates/stomp/0.8.4/dependencies","version_downloads":"/api/v1/crates/stomp/0.8.4/downloads"},"num":"0.8.4","updated_at":"2015-12-11T23:56:18Z","yanked":false},{"crate":"stomp","created_at":"2015-03-29T20:12:55Z","dl_path":"/api/v1/crates/stomp/0.8.3/download","downloads":12,"features":{},"id":7504,"links":{"authors":"/api/v1/crates/stomp/0.8.3/authors","dependencies":"/api/v1/crates/stomp/0.8.3/dependencies","version_downloads":"/api/v1/crates/stomp/0.8.3/downloads"},"num":"0.8.3","updated_at":"2015-12-11T23:56:18Z","yanked":false},{"crate":"stomp","created_at":"2015-03-25T23:37:33Z","dl_path":"/api/v1/crates/stomp/0.8.2/download","downloads":11,"features":{},"id":7144,"links":{"authors":"/api/v1/crates/stomp/0.8.2/authors","dependencies":"/api/v1/crates/stomp/0.8.2/dependencies","version_downloads":"/api/v1/crates/stomp/0.8.2/downloads"},"num":"0.8.2","updated_at":"2015-12-11T23:56:18Z","yanked":false},{"crate":"stomp","created_at":"2015-03-04T00:43:14Z","dl_path":"/api/v1/crates/stomp/0.8.1/download","downloads":16,"features":{},"id":5920,"links":{"authors":"/api/v1/crates/stomp/0.8.1/authors","dependencies":"/api/v1/crates/stomp/0.8.1/dependencies","version_downloads":"/api/v1/crates/stomp/0.8.1/downloads"},"num":"0.8.1","updated_at":"2015-12-11T23:56:18Z","yanked":false},{"crate":"stomp","created_at":"2015-02-08T22:51:45Z","dl_path":"/api/v1/crates/stomp/0.8.0/download","downloads":16,"features":{},"id":4760,"links":{"authors":"/api/v1/crates/stomp/0.8.0/authors","dependencies":"/api/v1/crates/stomp/0.8.0/dependencies","version_downloads":"/api/v1/crates/stomp/0.8.0/downloads"},"num":"0.8.0","updated_at":"2015-12-11T23:56:18Z","yanked":false},{"crate":"stomp","created_at":"2015-02-08T18:55:48Z","dl_path":"/api/v1/crates/stomp/0.7.0/download","downloads":15,"features":{},"id":4747,"links":{"authors":"/api/v1/crates/stomp/0.7.0/authors","dependencies":"/api/v1/crates/stomp/0.7.0/dependencies","version_downloads":"/api/v1/crates/stomp/0.7.0/downloads"},"num":"0.7.0","updated_at":"2015-12-11T23:56:18Z","yanked":false},{"crate":"stomp","created_at":"2015-02-05T18:46:21Z","dl_path":"/api/v1/crates/stomp/0.6.0/download","downloads":14,"features":{},"id":4554,"links":{"authors":"/api/v1/crates/stomp/0.6.0/authors","dependencies":"/api/v1/crates/stomp/0.6.0/dependencies","version_downloads":"/api/v1/crates/stomp/0.6.0/downloads"},"num":"0.6.0","updated_at":"2015-12-11T23:56:18Z","yanked":false},{"crate":"stomp","created_at":"2015-02-01T01:31:17Z","dl_path":"/api/v1/crates/stomp/0.5.2/download","downloads":14,"features":{},"id":4263,"links":{"authors":"/api/v1/crates/stomp/0.5.2/authors","dependencies":"/api/v1/crates/stomp/0.5.2/dependencies","version_downloads":"/api/v1/crates/stomp/0.5.2/downloads"},"num":"0.5.2","updated_at":"2015-12-11T23:56:18Z","yanked":false},{"crate":"stomp","created_at":"2015-01-30T04:05:57Z","dl_path":"/api/v1/crates/stomp/0.5.1/download","downloads":11,"features":{},"id":4139,"links":{"authors":"/api/v1/crates/stomp/0.5.1/authors","dependencies":"/api/v1/crates/stomp/0.5.1/dependencies","version_downloads":"/api/v1/crates/stomp/0.5.1/downloads"},"num":"0.5.1","updated_at":"2015-12-11T23:56:18Z","yanked":false},{"crate":"stomp","created_at":"2015-01-27T03:56:58Z","dl_path":"/api/v1/crates/stomp/0.5.0/download","downloads":9,"features":{},"id":3952,"links":{"authors":"/api/v1/crates/stomp/0.5.0/authors","dependencies":"/api/v1/crates/stomp/0.5.0/dependencies","version_downloads":"/api/v1/crates/stomp/0.5.0/downloads"},"num":"0.5.0","updated_at":"2015-12-11T23:56:18Z","yanked":false},{"crate":"stomp","created_at":"2015-01-25T05:52:52Z","dl_path":"/api/v1/crates/stomp/0.4.0/download","downloads":11,"features":{},"id":3468,"links":{"authors":"/api/v1/crates/stomp/0.4.0/authors","dependencies":"/api/v1/crates/stomp/0.4.0/dependencies","version_downloads":"/api/v1/crates/stomp/0.4.0/downloads"},"num":"0.4.0","updated_at":"2015-12-11T23:56:18Z","yanked":false},{"crate":"stomp","created_at":"2015-01-11T04:32:42Z","dl_path":"/api/v1/crates/stomp/0.3.7/download","downloads":12,"features":{},"id":2813,"links":{"authors":"/api/v1/crates/stomp/0.3.7/authors","dependencies":"/api/v1/crates/stomp/0.3.7/dependencies","version_downloads":"/api/v1/crates/stomp/0.3.7/downloads"},"num":"0.3.7","updated_at":"2015-12-11T23:56:18Z","yanked":false},{"crate":"stomp","created_at":"2015-01-06T02:23:22Z","dl_path":"/api/v1/crates/stomp/0.3.6/download","downloads":11,"features":{},"id":2284,"links":{"authors":"/api/v1/crates/stomp/0.3.6/authors","dependencies":"/api/v1/crates/stomp/0.3.6/dependencies","version_downloads":"/api/v1/crates/stomp/0.3.6/downloads"},"num":"0.3.6","updated_at":"2015-12-11T23:56:18Z","yanked":false},{"crate":"stomp","created_at":"2015-01-06T02:01:25Z","dl_path":"/api/v1/crates/stomp/0.3.5/download","downloads":10,"features":{},"id":2283,"links":{"authors":"/api/v1/crates/stomp/0.3.5/authors","dependencies":"/api/v1/crates/stomp/0.3.5/dependencies","version_downloads":"/api/v1/crates/stomp/0.3.5/downloads"},"num":"0.3.5","updated_at":"2015-12-11T23:56:18Z","yanked":false},{"crate":"stomp","created_at":"2014-12-21T16:24:24Z","dl_path":"/api/v1/crates/stomp/0.3.4/download","downloads":12,"features":{},"id":1455,"links":{"authors":"/api/v1/crates/stomp/0.3.4/authors","dependencies":"/api/v1/crates/stomp/0.3.4/dependencies","version_downloads":"/api/v1/crates/stomp/0.3.4/downloads"},"num":"0.3.4","updated_at":"2015-12-11T23:56:18Z","yanked":false},{"crate":"stomp","created_at":"2014-11-23T17:40:16Z","dl_path":"/api/v1/crates/stomp/0.3.3/download","downloads":13,"features":{},"id":561,"links":{"authors":"/api/v1/crates/stomp/0.3.3/authors","dependencies":"/api/v1/crates/stomp/0.3.3/dependencies","version_downloads":"/api/v1/crates/stomp/0.3.3/downloads"},"num":"0.3.3","updated_at":"2015-12-11T23:56:18Z","yanked":false}]}